{"$schema":"https://proj.org/schemas/v0.7/projjson.schema.json","type":"GeographicCRS","name":"UGRF","datum":{"type":"GeodeticReferenceFrame","name":"Uganda Geodetic Reference Frame","ellipsoid":{"name":"GRS 1980","semi_major_axis":6378137,"inverse_flattening":298.257222101}},"coordinate_system":{"subtype":"ellipsoidal","axis":[{"name":"Geodetic latitude","abbreviation":"Lat","direction":"north","unit":"degree"},{"name":"Geodetic longitude","abbreviation":"Lon","direction":"east","unit":"degree"},{"name":"Ellipsoidal height","abbreviation":"h","direction":"up","unit":"metre"}]},"scope":"Geodesy.","area":"Uganda.","bbox":{"south_latitude":-1.48,"west_longitude":29.57,"north_latitude":4.23,"east_longitude":35.01},"id":{"authority":"EPSG","code":10790}}