{"$schema":"https://proj.org/schemas/v0.7/projjson.schema.json","type":"GeographicCRS","name":"Rangiroa (MHPF 1966-68) geographiques (dms)","datum":{"type":"GeodeticReferenceFrame","name":"MHPF 1966-1968 (ATOLL RANGIROA OU RAIROA)","ellipsoid":{"name":"International 1924","semi_major_axis":6378388,"inverse_flattening":297}},"coordinate_system":{"subtype":"ellipsoidal","axis":[{"name":"Geodetic longitude","abbreviation":"Lon","direction":"east","unit":"degree"},{"name":"Geodetic latitude","abbreviation":"Lat","direction":"north","unit":"degree"}]},"scope":"LOCALE, HISTORIQUE","area":"RANGIROA (ARCHIPEL DES TUAMOTU)","bbox":{"south_latitude":-14.83,"west_longitude":-148,"north_latitude":-14.42,"east_longitude":-147.15},"id":{"authority":"IGNF","code":"RANGI68G"}}