{"$schema":"https://proj.org/schemas/v0.7/projjson.schema.json","type":"GeographicCRS","name":"GCS_PANAMA08_2011","datum":{"type":"GeodeticReferenceFrame","name":"PANAMA08_2011","ellipsoid":{"name":"GRS 1980","semi_major_axis":6378137,"inverse_flattening":298.257222101}},"coordinate_system":{"subtype":"ellipsoidal","axis":[{"name":"Geodetic latitude","abbreviation":"Lat","direction":"north","unit":"degree"},{"name":"Geodetic longitude","abbreviation":"Lon","direction":"east","unit":"degree"}]},"scope":"Not known.","area":"Panama - onshore and offshore.","bbox":{"south_latitude":5,"west_longitude":-84.32,"north_latitude":12.51,"east_longitude":-77.04},"id":{"authority":"ESRI","code":104646}}