{"$schema":"https://proj.org/schemas/v0.7/projjson.schema.json","type":"ProjectedCRS","name":"ETRS89/DREF91/2016 / UTM zone 33N","base_crs":{"type":"GeographicCRS","name":"ETRS89/DREF91/2016","datum":{"type":"GeodeticReferenceFrame","name":"ETRS89/DREF91 Realization 2016","ellipsoid":{"name":"GRS 1980","semi_major_axis":6378137,"inverse_flattening":298.257222101}},"coordinate_system":{"subtype":"ellipsoidal","axis":[{"name":"Geodetic latitude","abbreviation":"Lat","direction":"north","unit":"degree"},{"name":"Geodetic longitude","abbreviation":"Lon","direction":"east","unit":"degree"}]},"id":{"authority":"EPSG","code":10284}},"conversion":{"name":"UTM zone 33N","method":{"name":"Transverse Mercator","id":{"authority":"EPSG","code":9807}},"parameters":[{"name":"Latitude of natural origin","value":0,"unit":"degree","id":{"authority":"EPSG","code":8801}},{"name":"Longitude of natural origin","value":15,"unit":"degree","id":{"authority":"EPSG","code":8802}},{"name":"Scale factor at natural origin","value":0.9996,"unit":"unity","id":{"authority":"EPSG","code":8805}},{"name":"False easting","value":500000,"unit":"metre","id":{"authority":"EPSG","code":8806}},{"name":"False northing","value":0,"unit":"metre","id":{"authority":"EPSG","code":8807}}]},"coordinate_system":{"subtype":"Cartesian","axis":[{"name":"Easting","abbreviation":"E","direction":"east","unit":"metre"},{"name":"Northing","abbreviation":"N","direction":"north","unit":"metre"}]},"scope":"Cadastre, engineering survey.","area":"Germany - onshore and offshore east of 12°E, together with that part of Brandenburg state west of 12°E - Bayern, Berlin, Brandenburg (all state), Mecklenburg-Vorpommern, Sachsen, Sachsen-Anhalt, Thuringen.","bbox":{"south_latitude":47.46,"west_longitude":11.57,"north_latitude":55.03,"east_longitude":15.04},"id":{"authority":"EPSG","code":10733}}