{"$schema":"https://proj.org/schemas/v0.7/projjson.schema.json","type":"ProjectedCRS","name":"NAD83(2011) / ICS83-Mount Vernon (ftUS)","base_crs":{"name":"NAD83(2011)","datum":{"type":"GeodeticReferenceFrame","name":"NAD83 (National Spatial Reference System 2011)","ellipsoid":{"name":"GRS 1980","semi_major_axis":6378137,"inverse_flattening":298.257222101}},"coordinate_system":{"subtype":"ellipsoidal","axis":[{"name":"Geodetic latitude","abbreviation":"Lat","direction":"north","unit":"degree"},{"name":"Geodetic longitude","abbreviation":"Lon","direction":"east","unit":"degree"}]},"id":{"authority":"EPSG","code":6318}},"conversion":{"name":"Illinois Coordinate System of 1983 Mount Vernon zone (US survey foot)","method":{"name":"Lambert Conic Conformal (1SP)","id":{"authority":"EPSG","code":9801}},"parameters":[{"name":"Latitude of natural origin","value":38.45,"unit":"degree","id":{"authority":"EPSG","code":8801}},{"name":"Longitude of natural origin","value":-89.15,"unit":"degree","id":{"authority":"EPSG","code":8802}},{"name":"Scale factor at natural origin","value":1.000015,"unit":"unity","id":{"authority":"EPSG","code":8805}},{"name":"False easting","value":328000,"unit":{"type":"LinearUnit","name":"US survey foot","conversion_factor":0.304800609601219},"id":{"authority":"EPSG","code":8806}},{"name":"False northing","value":3773000,"unit":{"type":"LinearUnit","name":"US survey foot","conversion_factor":0.304800609601219},"id":{"authority":"EPSG","code":8807}}]},"coordinate_system":{"subtype":"Cartesian","axis":[{"name":"Northing","abbreviation":"N","direction":"north","unit":{"type":"LinearUnit","name":"US survey foot","conversion_factor":0.304800609601219}},{"name":"Easting","abbreviation":"E","direction":"east","unit":{"type":"LinearUnit","name":"US survey foot","conversion_factor":0.304800609601219}}]},"scope":"Engineering survey, topographic mapping (large and medium scale).","area":"United States (USA) - Illinois - counties of Clinton, Jefferson, Marion and Washington.","bbox":{"south_latitude":38.12,"west_longitude":-89.71,"north_latitude":38.83,"east_longitude":-88.69},"id":{"authority":"EPSG","code":23330}}