{"$schema":"https://proj.org/schemas/v0.7/projjson.schema.json","type":"ProjectedCRS","name":"NAD83(2011) / WISCRS La Crosse (ftUS)","base_crs":{"name":"NAD83(2011)","datum":{"type":"GeodeticReferenceFrame","name":"NAD83 (National Spatial Reference System 2011)","ellipsoid":{"name":"GRS 1980","semi_major_axis":6378137,"inverse_flattening":298.257222101}},"coordinate_system":{"subtype":"ellipsoidal","axis":[{"name":"Geodetic latitude","abbreviation":"Lat","direction":"north","unit":"degree"},{"name":"Geodetic longitude","abbreviation":"Lon","direction":"east","unit":"degree"}]},"id":{"authority":"EPSG","code":6318}},"conversion":{"name":"WISCRS La Crosse County (ftUS)","method":{"name":"Transverse Mercator","id":{"authority":"EPSG","code":9807}},"parameters":[{"name":"Latitude of natural origin","value":43.4511111111111,"unit":"degree","id":{"authority":"EPSG","code":8801}},{"name":"Longitude of natural origin","value":-91.3166666666667,"unit":"degree","id":{"authority":"EPSG","code":8802}},{"name":"Scale factor at natural origin","value":1.0000319985,"unit":"unity","id":{"authority":"EPSG","code":8805}},{"name":"False easting","value":427999.996,"unit":{"type":"LinearUnit","name":"US survey foot","conversion_factor":0.304800609601219},"id":{"authority":"EPSG","code":8806}},{"name":"False northing","value":0.011,"unit":{"type":"LinearUnit","name":"US survey foot","conversion_factor":0.304800609601219},"id":{"authority":"EPSG","code":8807}}]},"coordinate_system":{"subtype":"Cartesian","axis":[{"name":"Easting","abbreviation":"X","direction":"east","unit":{"type":"LinearUnit","name":"US survey foot","conversion_factor":0.304800609601219}},{"name":"Northing","abbreviation":"Y","direction":"north","unit":{"type":"LinearUnit","name":"US survey foot","conversion_factor":0.304800609601219}}]},"scope":"Engineering survey.","area":"United States (USA) - Wisconsin - La Crosse county.","bbox":{"south_latitude":43.72,"west_longitude":-91.43,"north_latitude":44.1,"east_longitude":-90.91},"id":{"authority":"EPSG","code":7615}}