{"$schema":"https://proj.org/schemas/v0.7/projjson.schema.json","type":"ProjectedCRS","name":"NAD_1983_2011_StatePlane_Alaska_4_FIPS_5004_Feet","base_crs":{"name":"NAD83(2011)","datum":{"type":"GeodeticReferenceFrame","name":"NAD83 (National Spatial Reference System 2011)","ellipsoid":{"name":"GRS 1980","semi_major_axis":6378137,"inverse_flattening":298.257222101}},"coordinate_system":{"subtype":"ellipsoidal","axis":[{"name":"Geodetic latitude","abbreviation":"Lat","direction":"north","unit":"degree"},{"name":"Geodetic longitude","abbreviation":"Lon","direction":"east","unit":"degree"}]},"id":{"authority":"EPSG","code":6318}},"conversion":{"name":"NAD_1983_2011_StatePlane_Alaska_4_FIPS_5004_Feet","method":{"name":"Transverse Mercator","id":{"authority":"EPSG","code":9807}},"parameters":[{"name":"Latitude of natural origin","value":54,"unit":"degree","id":{"authority":"EPSG","code":8801}},{"name":"Longitude of natural origin","value":-150,"unit":"degree","id":{"authority":"EPSG","code":8802}},{"name":"Scale factor at natural origin","value":0.9999,"unit":"unity","id":{"authority":"EPSG","code":8805}},{"name":"False easting","value":1640416.66666667,"unit":{"type":"LinearUnit","name":"US survey foot","conversion_factor":0.304800609601219},"id":{"authority":"EPSG","code":8806}},{"name":"False northing","value":0,"unit":{"type":"LinearUnit","name":"US survey foot","conversion_factor":0.304800609601219},"id":{"authority":"EPSG","code":8807}}]},"coordinate_system":{"subtype":"Cartesian","axis":[{"name":"Easting","abbreviation":"X","direction":"east","unit":{"type":"LinearUnit","name":"US survey foot","conversion_factor":0.304800609601219}},{"name":"Northing","abbreviation":"Y","direction":"north","unit":{"type":"LinearUnit","name":"US survey foot","conversion_factor":0.304800609601219}}]},"scope":"Not known.","area":"United States (USA) - Alaska - between 152°W and 148°W, onshore.","bbox":{"south_latitude":59.11,"west_longitude":-152.01,"north_latitude":70.63,"east_longitude":-147.99},"id":{"authority":"ESRI","code":102392}}