{"$schema":"https://proj.org/schemas/v0.7/projjson.schema.json","type":"ProjectedCRS","name":"NAD_1983_HARN_Adj_WI_Bayfield_Feet","base_crs":{"name":"GCS_NAD_1983_HARN_Adj_WI_Bayfield","datum":{"type":"GeodeticReferenceFrame","name":"D_NAD_1983_HARN_Adj_WI_BF","ellipsoid":{"name":"GRS_1980_Adj_WI_BF","semi_major_axis":6378411.351,"inverse_flattening":298.270051421254}},"coordinate_system":{"subtype":"ellipsoidal","axis":[{"name":"Geodetic latitude","abbreviation":"Lat","direction":"north","unit":"degree"},{"name":"Geodetic longitude","abbreviation":"Lon","direction":"east","unit":"degree"}]},"id":{"authority":"ESRI","code":104803}},"conversion":{"name":"NAD_1983_HARN_Adj_WI_Bayfield_Feet","method":{"name":"Lambert Conic Conformal (2SP)","id":{"authority":"EPSG","code":9802}},"parameters":[{"name":"Latitude of false origin","value":45.3333333333333,"unit":"degree","id":{"authority":"EPSG","code":8821}},{"name":"Longitude of false origin","value":-91.1527777777778,"unit":"degree","id":{"authority":"EPSG","code":8822}},{"name":"Latitude of 1st standard parallel","value":46.4138888888889,"unit":"degree","id":{"authority":"EPSG","code":8823}},{"name":"Latitude of 2nd standard parallel","value":46.925,"unit":"degree","id":{"authority":"EPSG","code":8824}},{"name":"Easting at false origin","value":750000,"unit":{"type":"LinearUnit","name":"US survey foot","conversion_factor":0.304800609601219},"id":{"authority":"EPSG","code":8826}},{"name":"Northing at false origin","value":0,"unit":{"type":"LinearUnit","name":"US survey foot","conversion_factor":0.304800609601219},"id":{"authority":"EPSG","code":8827}}]},"coordinate_system":{"subtype":"Cartesian","axis":[{"name":"Easting","abbreviation":"X","direction":"east","unit":{"type":"LinearUnit","name":"US survey foot","conversion_factor":0.304800609601219}},{"name":"Northing","abbreviation":"Y","direction":"north","unit":{"type":"LinearUnit","name":"US survey foot","conversion_factor":0.304800609601219}}]},"scope":"Not known.","area":"United States (USA) - Wisconsin.","bbox":{"south_latitude":42.48,"west_longitude":-92.89,"north_latitude":47.31,"east_longitude":-86.25},"id":{"authority":"ESRI","code":103944}}