{"$schema":"https://proj.org/schemas/v0.7/projjson.schema.json","type":"GeographicCRS","name":"ETRF2020","datum":{"type":"DynamicGeodeticReferenceFrame","name":"European Terrestrial Reference Frame 2020","frame_reference_epoch":1989,"ellipsoid":{"name":"GRS 1980","semi_major_axis":6378137,"inverse_flattening":298.257222101}},"coordinate_system":{"subtype":"ellipsoidal","axis":[{"name":"Geodetic latitude","abbreviation":"Lat","direction":"north","unit":"degree"},{"name":"Geodetic longitude","abbreviation":"Lon","direction":"east","unit":"degree"}]},"scope":"Geodesy.","area":"Europe - onshore and offshore - ETRF extent - approximately 16°W to 33°E and 33°N to 84°N.","bbox":{"south_latitude":33.26,"west_longitude":-16.1,"north_latitude":84.73,"east_longitude":38.01},"id":{"authority":"EPSG","code":10571},"remarks":"Replaces ETRF2014 (code 9069). ETRF2020 is technically superior to ETRF2000 but ETRF2000 and other previous realizations may be preferred for backward compatibility reasons. Differences between ETRF2020 and ETRF2000 can reach 7cm."}