{"$schema":"https://proj.org/schemas/v0.7/projjson.schema.json","type":"GeographicCRS","name":"RT38 (Stockholm)","datum":{"type":"GeodeticReferenceFrame","name":"Stockholm 1938 (Stockholm)","ellipsoid":{"name":"Bessel 1841","semi_major_axis":6377397.155,"inverse_flattening":299.1528128},"prime_meridian":{"name":"Stockholm","longitude":18.0582777777778}},"coordinate_system":{"subtype":"ellipsoidal","axis":[{"name":"Geodetic latitude","abbreviation":"Lat","direction":"north","unit":"degree"},{"name":"Geodetic longitude","abbreviation":"Lon","direction":"east","unit":"degree"}]},"scope":"Geodesy.","area":"Sweden - onshore.","bbox":{"south_latitude":55.28,"west_longitude":10.93,"north_latitude":69.07,"east_longitude":24.17},"id":{"authority":"EPSG","code":4814}}