{"$schema":"https://proj.org/schemas/v0.7/projjson.schema.json","type":"GeographicCRS","name":"WC05-IRF","datum":{"type":"GeodeticReferenceFrame","name":"WC05 Intermediate Reference Frame","ellipsoid":{"name":"GRS 1980","semi_major_axis":6378137,"inverse_flattening":298.257222101}},"coordinate_system":{"subtype":"ellipsoidal","axis":[{"name":"Geodetic latitude","abbreviation":"Lat","direction":"north","unit":"degree"},{"name":"Geodetic longitude","abbreviation":"Lon","direction":"east","unit":"degree"}]},"scope":"Engineering survey and topographic mapping for railway applications.","area":"United Kingdom (UK) - on or related to the west coast mainline rail route from London (Euston) via Carlisle to Glasgow.","bbox":{"south_latitude":51.4,"west_longitude":-4.33,"north_latitude":55.92,"east_longitude":-0.04},"id":{"authority":"EPSG","code":10628}}