{"$schema":"https://proj.org/schemas/v0.7/projjson.schema.json","type":"GeographicCRS","name":"UCS-2000","datum":{"type":"GeodeticReferenceFrame","name":"Ukraine 2000","ellipsoid":{"name":"Krassowsky 1940","semi_major_axis":6378245,"inverse_flattening":298.3}},"coordinate_system":{"subtype":"ellipsoidal","axis":[{"name":"Geodetic latitude","abbreviation":"Lat","direction":"north","unit":"degree"},{"name":"Geodetic longitude","abbreviation":"Lon","direction":"east","unit":"degree"}]},"scope":"Horizontal component of 3D system.","area":"Ukraine - onshore and offshore.","bbox":{"south_latitude":43.18,"west_longitude":22.15,"north_latitude":52.38,"east_longitude":40.18},"id":{"authority":"EPSG","code":5561}}