{"$schema":"https://proj.org/schemas/v0.7/projjson.schema.json","type":"ProjectedCRS","name":"Guam_Geodetic_Triangulation_Network_1963","base_crs":{"type":"GeographicCRS","name":"Guam 1963","datum":{"type":"GeodeticReferenceFrame","name":"Guam 1963","ellipsoid":{"name":"Clarke 1866","semi_major_axis":6378206.4,"inverse_flattening":294.9786982}},"coordinate_system":{"subtype":"ellipsoidal","axis":[{"name":"Longitude","abbreviation":"lon","direction":"east","unit":{"type":"AngularUnit","name":"Degree","conversion_factor":0.0174532925199433}},{"name":"Latitude","abbreviation":"lat","direction":"north","unit":{"type":"AngularUnit","name":"Degree","conversion_factor":0.0174532925199433}}]}},"conversion":{"name":"Guam_Geodetic_Triangulation_Network_1963","method":{"name":"Azimuthal Equidistant","id":{"authority":"EPSG","code":1125}},"parameters":[{"name":"Latitude of natural origin","value":13.4724663527778,"unit":{"type":"AngularUnit","name":"Degree","conversion_factor":0.0174532925199433},"id":{"authority":"EPSG","code":8801}},{"name":"Longitude of natural origin","value":144.748750705556,"unit":{"type":"AngularUnit","name":"Degree","conversion_factor":0.0174532925199433},"id":{"authority":"EPSG","code":8802}},{"name":"False easting","value":50000,"unit":"metre","id":{"authority":"EPSG","code":8806}},{"name":"False northing","value":50000,"unit":"metre","id":{"authority":"EPSG","code":8807}}]},"coordinate_system":{"subtype":"Cartesian","axis":[{"name":"Easting","abbreviation":"E","direction":"east","unit":"metre"},{"name":"Northing","abbreviation":"N","direction":"north","unit":"metre"}]},"scope":"Not known.","area":"Guam - onshore and offshore.","bbox":{"south_latitude":10.95,"west_longitude":141.19,"north_latitude":15.91,"east_longitude":148.18},"id":{"authority":"ESRI","code":102239}}