{"$schema":"https://proj.org/schemas/v0.7/projjson.schema.json","type":"GeographicCRS","name":"GCS_Venus_1985","datum":{"type":"GeodeticReferenceFrame","name":"D_Venus_1985","ellipsoid":{"name":"Venus_1985_IAU_IAG_COSPAR","radius":6051000},"prime_meridian":{"name":"Reference_Meridian","longitude":0}},"coordinate_system":{"subtype":"ellipsoidal","axis":[{"name":"Geodetic latitude","abbreviation":"Lat","direction":"north","unit":"degree"},{"name":"Geodetic longitude","abbreviation":"Lon","direction":"east","unit":"degree"}]},"scope":"Not known.","area":"World.","bbox":{"south_latitude":-90,"west_longitude":-180,"north_latitude":90,"east_longitude":180},"id":{"authority":"ESRI","code":104901}}