{"$schema":"https://proj.org/schemas/v0.7/projjson.schema.json","type":"ProjectedCRS","name":"NAD_1983_HARN_Adj_WI_St_Croix_Meters","base_crs":{"name":"GCS_NAD_1983_HARN_Adj_WI_StCroix","datum":{"type":"GeodeticReferenceFrame","name":"D_NAD_1983_HARN_Adj_WI_SC","ellipsoid":{"name":"GRS_1980_Adj_WI_SC","semi_major_axis":6378412.511,"inverse_flattening":298.270105665679}},"coordinate_system":{"subtype":"ellipsoidal","axis":[{"name":"Geodetic latitude","abbreviation":"Lat","direction":"north","unit":"degree"},{"name":"Geodetic longitude","abbreviation":"Lon","direction":"east","unit":"degree"}]},"id":{"authority":"ESRI","code":104855}},"conversion":{"name":"NAD_1983_HARN_Adj_WI_St_Croix_Meters","method":{"name":"Transverse Mercator","id":{"authority":"EPSG","code":9807}},"parameters":[{"name":"Latitude of natural origin","value":44.0361111111111,"unit":"degree","id":{"authority":"EPSG","code":8801}},{"name":"Longitude of natural origin","value":-92.6333333333333,"unit":"degree","id":{"authority":"EPSG","code":8802}},{"name":"Scale factor at natural origin","value":0.999995,"unit":"unity","id":{"authority":"EPSG","code":8805}},{"name":"False easting","value":165506.731013462,"unit":"metre","id":{"authority":"EPSG","code":8806}},{"name":"False northing","value":0,"unit":"metre","id":{"authority":"EPSG","code":8807}}]},"coordinate_system":{"subtype":"Cartesian","axis":[{"name":"Easting","abbreviation":"E","direction":"east","unit":"metre"},{"name":"Northing","abbreviation":"N","direction":"north","unit":"metre"}]},"scope":"Not known.","area":"United States (USA) - Wisconsin.","bbox":{"south_latitude":42.48,"west_longitude":-92.89,"north_latitude":47.31,"east_longitude":-86.25},"id":{"authority":"ESRI","code":103835}}